nzgeom/__init__.py
nzgeom/coastlines.py
nzgeom/regions.py
nzgeom/data/coastlines/nz-coastlines-and-islands-polygons-topo-150k.gpkg
nzgeom/data/coastlines/nz-coastlines-and-islands-polygons-topo-150k.txt
nzgeom/data/coastlines/nz-coastlines-and-islands-polygons-topo-150k.xml
nzgeom/data/regions/regional-council-2018-generalised.gpkg
nzgeom/data/regions/regional-council-2018-generalised.txt
nzgeom/data/regions/regional-council-2018-generalised.xml
nzgeom-1.0.1.dist-info/licenses/LICENSE.txt
tests/nzgeom_test.py
nzgeom-1.0.1.dist-info/METADATA
nzgeom-1.0.1.dist-info/WHEEL
nzgeom-1.0.1.dist-info/top_level.txt
nzgeom-1.0.1.dist-info/RECORD
