Metadata-Version: 2.4
Name: nzgeom
Version: 1.0.1
Summary: provide geospatial geometry for NZ coastlines and administrative regions
Author-email: "Timothy W. Hilton" <t.hilton@gns.cri.nz>
Project-URL: Homepage, https://github.com/Timothy-W-Hilton/NZ_geometries
Project-URL: Bug Tracker, https://github.com/Timothy-W-Hilton/NZ_geometries/issues
Classifier: Programming Language :: Python :: 3
Classifier: License :: OSI Approved :: MIT License
Classifier: Operating System :: OS Independent
Requires-Python: >=3.9
License-File: LICENSE.txt
Requires-Dist: geopandas
Requires-Dist: rtree
Requires-Dist: importlib_resources; python_version < "3.10"
Dynamic: license-file
